riehmcolor2/__init__.py
riehmcolor2_alex555155-0.1.dist-info/LICENSE
riehmcolor2_alex555155-0.1.dist-info/METADATA
riehmcolor2_alex555155-0.1.dist-info/WHEEL
riehmcolor2_alex555155-0.1.dist-info/top_level.txt
riehmcolor2_alex555155-0.1.dist-info/RECORD
