Metadata-Version: 2.1
Name: riehmcolor2-alex555155
Version: 0.1
Summary: Color analysis suite
Home-page: UNKNOWN
Author: Alex Riehm
Author-email: kf5uum@gmail.com
License: UNKNOWN
Platform: UNKNOWN
Classifier: Programming Language :: Python :: 3
Classifier: License :: OSI Approved :: MIT License
Classifier: Operating System :: OS Independent
Requires-Python: >=3.6
